controller.v
module controller (
	clk,
	reset,
	Instr,
	ALUFlags,
	PCWrite,
	MemWrite,
	RegWrite,
	IRWrite,
	AdrSrc,
	RegSrc,
	ALUSrcA,
	ALUSrcB,
	ResultSrc,
	ImmSrc,
	ALUControl
);
	input wire clk;
	input wire reset;
	input wire [31:12] Instr;
	input wire [3:0] ALUFlags;
	
	output wire PCWrite;
	output wire MemWrite;
	output wire RegWrite;
	output wire IRWrite;
	output wire AdrSrc;
	output wire [1:0] RegSrc;
	output wire [1:0] ALUSrcA;
	output wire [1:0] ALUSrcB;
	output wire [1:0] ResultSrc;
	output wire [1:0] ImmSrc;
	output wire [1:0] ALUControl;

	wire [1:0] FlagW;
	wire PCS;
	wire NextPC;
	wire RegW;
	wire MemW;
	decode dec(
		.clk(clk),
		.reset(reset),
		.Op(Instr[27:26]),
		.Funct(Instr[25:20]),
		.Rd(Instr[15:12]),
		.FlagW(FlagW),
		.PCS(PCS),
		.NextPC(NextPC),
		.RegW(RegW),
		.MemW(MemW),
		.IRWrite(IRWrite),
		.AdrSrc(AdrSrc),
		.ResultSrc(ResultSrc),
		.ALUSrcA(ALUSrcA),
		.ALUSrcB(ALUSrcB),
		.ImmSrc(ImmSrc),
		.RegSrc(RegSrc),
		.ALUControl(ALUControl)
	);
	condlogic cl(
		.clk(clk),
		.reset(reset),
		.Cond(Instr[31:28]),
		.ALUFlags(ALUFlags),
		.FlagW(FlagW),
		.PCS(PCS),
		.NextPC(NextPC),
		.RegW(RegW),
		.MemW(MemW),
		.PCWrite(PCWrite),
		.RegWrite(RegWrite),
		.MemWrite(MemWrite)
	);
endmodule

module decode (
	clk,
	reset,
	Op,
	Funct,
	Rd,
	FlagW,
	PCS,
	NextPC,
	RegW,
	MemW,
	IRWrite,
	AdrSrc,
	ResultSrc,
	ALUSrcA,
	ALUSrcB,
	ImmSrc,
	RegSrc,
	ALUControl
);
	input wire clk;
	input wire reset;
	input wire [1:0] Op;
	input wire [5:0] Funct;
	input wire [3:0] Rd;
	output reg [1:0] FlagW;
	output wire PCS;
	output wire NextPC;
	output wire RegW;
	output wire MemW;
	output wire IRWrite;
	output wire AdrSrc;
	output wire [1:0] ResultSrc;
	output wire [1:0] ALUSrcA;
	output wire [1:0] ALUSrcB;
	output wire [1:0] ImmSrc;
	output reg [1:0] RegSrc;
	output reg [1:0] ALUControl;
	wire Branch;
	wire ALUOp;

	// Main FSM
	mainfsm fsm(
		.clk(clk),
		.reset(reset),
		.Op(Op),
		.Funct(Funct),
		.IRWrite(IRWrite),
		.AdrSrc(AdrSrc),
		.ALUSrcA(ALUSrcA),
		.ALUSrcB(ALUSrcB),
		.ResultSrc(ResultSrc),
		.NextPC(NextPC),
		.RegW(RegW),
		.MemW(MemW),
		.Branch(Branch),
		.ALUOp(ALUOp)
	);

	// ADD CODE BELOW
	// Add code for the ALU Decoder and PC Logic.
	// Remember, you may reuse code from previous labs.


	// ALU Decoder
	always @(*)
		if (ALUOp) begin
			case (Funct[4:1])
				4'b0100: ALUControl = 2'b00; // ADD
				4'b0010: ALUControl = 2'b01; // SUB
				4'b0000: ALUControl = 2'b10; // AND
				4'b1100: ALUControl = 2'b11; // ORR
				default: ALUControl = 2'bxx;
			endcase
			FlagW[1] = Funct[0];
			FlagW[0] = Funct[0] & ((ALUControl == 2'b00) | (ALUControl == 2'b01));
		end
		else begin
			ALUControl = 2'b00;
			FlagW = 2'b00;
		end
	
	// PC Logic
	assign PCS = ((Rd == 4'b1111) & RegW) | Branch;

	// Add code for the Instruction Decoder (Instr Decoder) below.
	// Recall that the input to Instr Decoder is Op, and the outputs are
	// ImmSrc and RegSrc. We've completed the ImmSrc logic for you.

	// Instr Decoder
	assign ImmSrc = Op;
	always @(*)
		case (Op)
			2'b00: RegSrc = 2'b00;
			2'b01: RegSrc = 2'b10;
			2'b10: RegSrc = 2'b01;
			default: RegSrc = 2'bxx;
		endcase
endmodule

module mainfsm (
	clk,
	reset,
	Op,
	Funct,
	IRWrite,
	AdrSrc,
	ALUSrcA,
	ALUSrcB,
	ResultSrc,
	NextPC,
	RegW,
	MemW,
	Branch,
	ALUOp
);
	input wire clk;
	input wire reset;
	input wire [1:0] Op;
	input wire [5:0] Funct;
	output wire IRWrite;
	output wire AdrSrc;
	output wire [1:0] ALUSrcA;
	output wire [1:0] ALUSrcB;
	output wire [1:0] ResultSrc;
	output wire NextPC;
	output wire RegW;
	output wire MemW;
	output wire Branch;
	output wire ALUOp;
	reg [3:0] state;
	reg [3:0] nextstate;
	reg [12:0] controls;
	
	localparam [3:0] FETCH = 0;
	localparam [3:0] DECODE = 1;
	localparam [3:0] MEMADR = 2;
	localparam [3:0] MEMRD = 3;
	localparam [3:0] MEMWB = 4;
	localparam [3:0] MEMWR = 5;
	localparam [3:0] EXECUTER = 6;
	localparam [3:0] EXECUTEI = 7;
	localparam [3:0] ALUWB = 8;
	localparam [3:0] BRANCH = 9;
	localparam [3:0] UNKNOWN = 10;

	// state register
	always @(posedge clk or posedge reset)
		if (reset)
			state <= FETCH;
		else
			state <= nextstate;
	

	// ADD CODE BELOW
  	// Finish entering the next state logic below.  We've completed the 
  	// first two states, FETCH and DECODE, for you.

  	// next state logic
	always @(*)
		casex (state)
			FETCH: nextstate = DECODE;
			DECODE:
				case (Op)
					2'b00:
						if (Funct[5])
							nextstate = EXECUTEI;
						else
							nextstate = EXECUTER;
					2'b01: nextstate = MEMADR;
					2'b10: nextstate = BRANCH;
					default: nextstate = UNKNOWN;
				endcase
			EXECUTER: nextstate = ALUWB;
			EXECUTEI: nextstate = ALUWB;
			MEMADR: 
				if(Funct[0]) nextstate = MEMRD; // LDR
				else nextstate = MEMWR; // STR
			MEMRD: nextstate = MEMWB;
			default: nextstate = FETCH;
		endcase

	// ADD CODE BELOW
	// Finish entering the output logic below.  We've entered the
	// output logic for the first two states, FETCH and DECODE, for you.

	// state-dependent output logic
	always @(*)
		case (state)
			FETCH: controls = 13'b1000101001100;
			DECODE: controls = 13'b0000001001100;
			EXECUTER: controls = 13'b0000000000001;
			EXECUTEI: controls = 13'b0000000000011;
			ALUWB: controls = 13'b0001000000000;
			MEMADR: controls = 13'b0000000000010;
			MEMWR: controls = 13'b0010010000000; // MemWrite
			MEMRD: controls = 13'b0000010000000; // MemRead
			MEMWB: controls = 13'b0001000100000;
			BRANCH: controls = 13'b0100001010010;
			default: controls = 13'bxxxxxxxxxxxxx;
		endcase
	assign {NextPC, Branch, MemW, RegW, IRWrite, AdrSrc, ResultSrc, ALUSrcA, ALUSrcB, ALUOp} = controls;
endmodule

// ADD CODE BELOW
// Add code for the condlogic and condcheck modules. Remember, you may
// reuse code from prior labs.
module condlogic (
	clk,
	reset,
	Cond,
	ALUFlags,
	FlagW,
	PCS,
	NextPC,
	RegW,
	MemW,
	PCWrite,
	RegWrite,
	MemWrite
);
	input wire clk;
	input wire reset;
	input wire [3:0] Cond;
	input wire [3:0] ALUFlags;
	input wire [1:0] FlagW;
	input wire PCS;
	input wire NextPC;
	input wire RegW;
	input wire MemW;
	output wire PCWrite;
	output wire RegWrite;
	output wire MemWrite;
	wire [1:0] FlagWrite;
	wire [3:0] Flags;
	wire CondEx;

	flopenr #(2) flagreg1(
		.clk(clk),
		.reset(reset),
		.en(FlagWrite[1]),
		.d(ALUFlags[3:2]),
		.q(Flags[3:2])
	);

	flopenr #(2) flagreg0(
		.clk(clk),
		.reset(reset),
		.en(FlagWrite[0]),
		.d(ALUFlags[1:0]),
		.q(Flags[1:0])
	);
	
	condcheck cc(
		.Cond(Cond),
		.Flags(Flags),
		.CondEx(CondEx)
	);

	// Delay writing flags until ALUWB state
	flopr #(2) flagwritereg(
		.clk(clk),
		.reset(reset),
		.d(FlagW & {2 {CondEx}}),
		.q(FlagWrite)
	);

	// ADD CODE HERE

	assign FlagWrite = FlagW & {2 {CondEx}};
	assign RegWrite = RegW & CondEx;
	assign MemWrite = MemW & CondEx;
	assign PCWrite = (PCS & CondEx) | NextPC;

endmodule

module condcheck (
	Cond,
	Flags,
	CondEx
);
	input wire [3:0] Cond;
	input wire [3:0] Flags;
	output reg CondEx;

	wire neg, zero, carry, overflow, ge;
	assign {neg, zero, carry, overflow} = Flags;
	assign ge = neg == overflow;
	always @(*)
		case (Cond)
			4'b0000: CondEx = zero;
			4'b0001: CondEx = ~zero;
			4'b0010: CondEx = carry;
			4'b0011: CondEx = ~carry;
			4'b0100: CondEx = neg;
			4'b0101: CondEx = ~neg;
			4'b0110: CondEx = overflow;
			4'b0111: CondEx = ~overflow;
			4'b1000: CondEx = carry & ~zero;
			4'b1001: CondEx = ~(carry & ~zero);
			4'b1010: CondEx = ge;
			4'b1011: CondEx = ~ge;
			4'b1100: CondEx = ~zero & ge;
			4'b1101: CondEx = ~(~zero & ge);
			4'b1110: CondEx = 1'b1;
			default: CondEx = 1'bx;
		endcase
endmodule

module flopenr (
	clk,
	reset,
	en,
	d,
	q
);
	parameter WIDTH = 8;
	input wire clk;
	input wire reset;
	input wire en;
	input wire [WIDTH - 1:0] d;
	output reg [WIDTH - 1:0] q;
	always @(posedge clk or posedge reset)
		if (reset)
			q <= 0;
		else if (en)
			q <= d;
endmodule


module flopr (
	clk,
	reset,
	d,
	q,
);
	parameter WIDTH = 8;
	input wire clk;
	input wire reset;
	input wire [WIDTH - 1:0] d;
	output reg [WIDTH - 1:0] q;

 	always @(posedge clk or posedge reset)
		if (reset) 
			q <= 0;
		else 
			q <= d;
endmodule

controller_tb.v
`include "controller.v"
`timescale 1ns / 1ps

module controller_tb;
    // inputs
    reg clk;
    reg reset;
    reg [31:12] Instr;
    reg [3:0] ALUFlags;

    // outputs
    wire PCWrite;
    wire MemWrite;
    wire RegWrite;
    wire IRWrite;
    wire AdrSrc;
    wire [1:0] RegSrc;
    wire [1:0] ALUSrcA;
    wire [1:0] ALUSrcB;
    wire [1:0] ResultSrc;
    wire [1:0] ImmSrc;
    wire [1:0] ALUControl;
    

	controller c(
		.clk(clk),
		.reset(reset),
		.Instr(Instr),
		.ALUFlags(ALUFlags),
		.PCWrite(PCWrite),
		.MemWrite(MemWrite),
		.RegWrite(RegWrite),
		.IRWrite(IRWrite),
		.AdrSrc(AdrSrc),
		.RegSrc(RegSrc),
		.ALUSrcA(ALUSrcA),
		.ALUSrcB(ALUSrcB),
		.ResultSrc(ResultSrc),
		.ImmSrc(ImmSrc),
		.ALUControl(ALUControl)
	);
    

    initial begin
		$dumpfile("controller_tb.vcd");
		$dumpvars;
        reset <= 1; #10 ; reset <= 0;
    end

    always begin
        clk <= 1; #5; clk <= 0; #5;
    end
    
	initial begin
        #10;
        // 20'b11100000010011110000
        Instr = 20'b11100000010011110000;   // MAIN     SUB R0, R15, R15     ; R0 = 0
        ALUFlags = 4'b0100;
    
        #40;
        Instr = 20'b11100010100000000010;   //          ADD R2, R0, #5       ; R2 = 5
        ALUFlags = 4'b0000;
        #40;
        Instr = 20'b11100010100000000011;   //          ADD R3, R0, #12      ; R3 = 12
        ALUFlags = 4'b0000;
        #40;
        Instr = 20'b11100010010000110111;   //          SUB R7, R3, #9       ; R7 = 3
        ALUFlags = 4'b0000;
        #40;
        Instr = 20'b11100001100001110100;   //          ORR R4, R7, R2       ; R4 = 3 OR 5 = 7 
        ALUFlags = 4'b0000;
        #40;
        Instr = 20'b11100000000000110101;   //          AND R5, R3, R4    	; R5 = 12 AND 7 = 4
        ALUFlags = 4'b0000;
        #40;
        Instr = 20'b11100000100001010101;   //          ADD R5, R5, R4    	; R5 = 4 + 7 = 11
        ALUFlags = 4'b0000;
        #40;
        Instr = 20'b11100000010101011000;   //          SUBS R8, R5, R7    	; R8 <= 11 - 3 = 8, set Flags
        ALUFlags = 4'b0010;
        #40;
        Instr = 20'b00001010000000000000;   //          BEQ END        		; shouldn't be taken 
        ALUFlags = 4'b0000;
        #30;
        Instr = 20'b11100000010100111000;   //          SUBS R8, R3, R4    	; R8 = 12 - 7  = 5
        ALUFlags = 4'b0000;
        #40;
        Instr = 20'b10101010000000000000;   //          BGE AROUND       	; should be taken 
        ALUFlags = 4'b0000;
        #30;
        Instr = 20'b11100010100000000101;   //          ADD R5, R0, #0     	; should be skipped
        ALUFlags = 4'b0000;
        #40;
        Instr = 20'b11100000010101111000;   // AROUND   SUBS R8, R7, R2   	; R8 = 3 - 5 = -2, set Flags
        ALUFlags = 4'b1000;
        #40;
        Instr = 20'b10110010100001010111;   //          ADDLT R7, R5, #1  	; R7 = 11 + 1 = 12
        ALUFlags = 4'b0000;
        #40;
        Instr = 20'b11100000010001110111;   //          SUB R7, R7, R2    	; R7 = 12 - 5 = 7
        ALUFlags = 4'b0000;
        #40;
        Instr = 20'b11100101100000110111;   //          STR R7, [R3, #84]  	; mem[12+84] = 7
        ALUFlags = 4'b0000;
        #40;
        Instr = 20'b11100101100100000010;   //          LDR R2, [R0, #96]  	; R2 = mem[96] = 7
        ALUFlags = 4'b0000;
        #50;
        Instr = 20'b11100000100011111111;   //          ADD R15, R15, R0	; PC <- PC + 8 (skips next)
        ALUFlags = 4'b0000;
        #40;
        Instr = 20'b11100010100000000010;   //          ADD R2, R0, #14    	; shouldn't happen
        ALUFlags = 4'b0000;
        #40;
        Instr = 20'b11101010000000000000;   //          B END             	; always taken
        ALUFlags = 4'b0000;
        #30;
        Instr = 20'b11100010100000000010;   //          ADD R2, R0, #13   	; shouldn't happen
        ALUFlags = 4'b0000;
        #40;
        Instr = 20'b11100010100000000010;   //          ADD R2, R0, #10		; shouldn't happen
        ALUFlags = 4'b0000;
        #40;
        Instr = 20'b11100101100000000010;   // END      STR R2, [R0, #100] 	; mem[100] = 7
        ALUFlags = 4'b0000;
        #40;
        $finish;
    end

    // Solo falta:
    // Completar los flags (si es que faltan)

endmodule

// 11100101100100000010

controller_tb.vcd
$date
	Sat Nov 05 19:16:19 2022
$end
$version
	Icarus Verilog
$end
$timescale
	1ps
$end
$scope module controller_tb $end
$var wire 2 ! ResultSrc [1:0] $end
$var wire 1 " RegWrite $end
$var wire 2 # RegSrc [1:0] $end
$var wire 1 $ PCWrite $end
$var wire 1 % MemWrite $end
$var wire 2 & ImmSrc [1:0] $end
$var wire 1 ' IRWrite $end
$var wire 1 ( AdrSrc $end
$var wire 2 ) ALUSrcB [1:0] $end
$var wire 2 * ALUSrcA [1:0] $end
$var wire 2 + ALUControl [1:0] $end
$var reg 4 , ALUFlags [3:0] $end
$var reg 20 - Instr [31:12] $end
$var reg 1 . clk $end
$var reg 1 / reset $end
$scope module c $end
$var wire 4 0 ALUFlags [3:0] $end
$var wire 20 1 Instr [31:12] $end
$var wire 1 . clk $end
$var wire 1 / reset $end
$var wire 2 2 ResultSrc [1:0] $end
$var wire 1 " RegWrite $end
$var wire 1 3 RegW $end
$var wire 2 4 RegSrc [1:0] $end
$var wire 1 $ PCWrite $end
$var wire 1 5 PCS $end
$var wire 1 6 NextPC $end
$var wire 1 % MemWrite $end
$var wire 1 7 MemW $end
$var wire 2 8 ImmSrc [1:0] $end
$var wire 1 ' IRWrite $end
$var wire 2 9 FlagW [1:0] $end
$var wire 1 ( AdrSrc $end
$var wire 2 : ALUSrcB [1:0] $end
$var wire 2 ; ALUSrcA [1:0] $end
$var wire 2 < ALUControl [1:0] $end
$scope module cl $end
$var wire 4 = ALUFlags [3:0] $end
$var wire 4 > Cond [3:0] $end
$var wire 2 ? FlagWrite [1:0] $end
$var wire 1 % MemWrite $end
$var wire 1 $ PCWrite $end
$var wire 1 " RegWrite $end
$var wire 1 . clk $end
$var wire 1 / reset $end
$var wire 1 3 RegW $end
$var wire 1 5 PCS $end
$var wire 1 6 NextPC $end
$var wire 1 7 MemW $end
$var wire 4 @ Flags [3:0] $end
$var wire 2 A FlagW [1:0] $end
$var wire 1 B CondEx $end
$scope module cc $end
$var wire 4 C Cond [3:0] $end
$var wire 4 D Flags [3:0] $end
$var wire 1 E ge $end
$var wire 1 F zero $end
$var wire 1 G overflow $end
$var wire 1 H neg $end
$var wire 1 I carry $end
$var reg 1 B CondEx $end
$upscope $end
$scope module flagreg0 $end
$var wire 1 . clk $end
$var wire 2 J d [1:0] $end
$var wire 1 K en $end
$var wire 1 / reset $end
$var parameter 32 L WIDTH $end
$var reg 2 M q [1:0] $end
$upscope $end
$scope module flagreg1 $end
$var wire 1 . clk $end
$var wire 2 N d [1:0] $end
$var wire 1 O en $end
$var wire 1 / reset $end
$var parameter 32 P WIDTH $end
$var reg 2 Q q [1:0] $end
$upscope $end
$scope module flagwritereg $end
$var wire 1 . clk $end
$var wire 2 R d [1:0] $end
$var wire 1 / reset $end
$var parameter 32 S WIDTH $end
$var reg 2 T q [1:0] $end
$upscope $end
$upscope $end
$scope module dec $end
$var wire 6 U Funct [5:0] $end
$var wire 2 V ImmSrc [1:0] $end
$var wire 2 W Op [1:0] $end
$var wire 1 5 PCS $end
$var wire 4 X Rd [3:0] $end
$var wire 1 . clk $end
$var wire 1 / reset $end
$var wire 2 Y ResultSrc [1:0] $end
$var wire 1 3 RegW $end
$var wire 1 6 NextPC $end
$var wire 1 7 MemW $end
$var wire 1 ' IRWrite $end
$var wire 1 Z Branch $end
$var wire 1 ( AdrSrc $end
$var wire 2 [ ALUSrcB [1:0] $end
$var wire 2 \ ALUSrcA [1:0] $end
$var wire 1 ] ALUOp $end
$var reg 2 ^ ALUControl [1:0] $end
$var reg 2 _ FlagW [1:0] $end
$var reg 2 ` RegSrc [1:0] $end
$scope module fsm $end
$var wire 6 a Funct [5:0] $end
$var wire 2 b Op [1:0] $end
$var wire 1 . clk $end
$var wire 1 / reset $end
$var wire 2 c ResultSrc [1:0] $end
$var wire 1 3 RegW $end
$var wire 1 6 NextPC $end
$var wire 1 7 MemW $end
$var wire 1 ' IRWrite $end
$var wire 1 Z Branch $end
$var wire 1 ( AdrSrc $end
$var wire 2 d ALUSrcB [1:0] $end
$var wire 2 e ALUSrcA [1:0] $end
$var wire 1 ] ALUOp $end
$var parameter 4 f ALUWB $end
$var parameter 4 g BRANCH $end
$var parameter 4 h DECODE $end
$var parameter 4 i EXECUTEI $end
$var parameter 4 j EXECUTER $end
$var parameter 4 k FETCH $end
$var parameter 4 l MEMADR $end
$var parameter 4 m MEMRD $end
$var parameter 4 n MEMWB $end
$var parameter 4 o MEMWR $end
$var parameter 4 p UNKNOWN $end
$var reg 13 q controls [12:0] $end
$var reg 4 r nextstate [3:0] $end
$var reg 4 s state [3:0] $end
$upscope $end
$upscope $end
$upscope $end
$upscope $end
$enddefinitions $end
$comment Show the parameter values. $end
$dumpall
b1010 p
b101 o
b100 n
b11 m
b10 l
b0 k
b110 j
b111 i
b1 h
b1001 g
b1000 f
b10 S
b10 P
b10 L
$end
#0
$dumpvars
b0 s
b1 r
b1000101001100 q
b1 e
b10 d
b10 c
bx b
bx a
bx `
b0 _
b0 ^
0]
b1 \
b10 [
0Z
b10 Y
bx X
bx W
bx V
bx U
b0 T
b0 R
b0 Q
0O
bx N
b0 M
0K
bx J
0I
0H
0G
0F
1E
b0 D
bx C
xB
b0 A
b0 @
b0 ?
bx >
bx =
b0 <
b1 ;
b10 :
b0 9
bx 8
07
16
05
bx 4
03
b10 2
bx 1
bx 0
1/
1.
bx -
bx ,
b0 +
b1 *
b10 )
0(
1'
bx &
0%
1$
bx #
0"
b10 !
$end
#5000
0.
#10000
0$
06
0'
b1001100 q
b110 r
b1 s
1.
0/
b0 #
b0 4
b0 `
1B
b1 N
b0 J
b0 &
b0 8
b0 V
b0 W
b0 b
b100 U
b100 a
b0 X
b1110 >
b1110 C
b100 ,
b100 0
b100 =
b11100000010011110000 -
b11100000010011110000 1
#15000
0.
#20000
b1 +
b1 <
b1 ^
b0 !
b0 2
b0 Y
b0 c
b0 *
b0 ;
b0 \
b0 e
b0 )
b0 :
b0 [
b0 d
1]
b1 q
b1000 r
b110 s
1.
#25000
0.
#30000
1"
b0 +
b0 <
b0 ^
13
0]
b1000000000 q
b0 r
b1000 s
1.
#35000
0.
#40000
1$
0"
16
03
1'
b10 !
b10 2
b10 Y
b10 c
b1 *
b1 ;
b1 \
b1 e
b10 )
b10 :
b10 [
b10 d
b1000101001100 q
b1 r
b0 s
1.
#45000
0.
#50000
0$
06
0'
b1001100 q
b111 r
b1 s
1.
b0 N
b101000 U
b101000 a
b10 X
b0 ,
b0 0
b0 =
b11100010100000000010 -
b11100010100000000010 1
#55000
0.
#60000
b0 !
b0 2
b0 Y
b0 c
b0 *
b0 ;
b0 \
b0 e
b1 )
b1 :
b1 [
b1 d
1]
b11 q
b1000 r
b111 s
1.
#65000
0.
#70000
1"
13
b0 )
b0 :
b0 [
b0 d
0]
b1000000000 q
b0 r
b1000 s
1.
#75000
0.
#80000
1$
0"
16
03
1'
b10 !
b10 2
b10 Y
b10 c
b1 *
b1 ;
b1 \
b1 e
b10 )
b10 :
b10 [
b10 d
b1000101001100 q
b1 r
b0 s
1.
#85000
0.
#90000
0$
06
0'
b1001100 q
b111 r
b1 s
1.
b11 X
b11100010100000000011 -
b11100010100000000011 1
#95000
0.
#100000
b0 !
b0 2
b0 Y
b0 c
b0 *
b0 ;
b0 \
b0 e
b1 )
b1 :
b1 [
b1 d
1]
b11 q
b1000 r
b111 s
1.
#105000
0.
#110000
1"
13
b0 )
b0 :
b0 [
b0 d
0]
b1000000000 q
b0 r
b1000 s
1.
#115000
0.
#120000
1$
0"
16
03
1'
b10 !
b10 2
b10 Y
b10 c
b1 *
b1 ;
b1 \
b1 e
b10 )
b10 :
b10 [
b10 d
b1000101001100 q
b1 r
b0 s
1.
#125000
0.
#130000
0$
06
0'
b1001100 q
b111 r
b1 s
1.
b100100 U
b100100 a
b111 X
b11100010010000110111 -
b11100010010000110111 1
#135000
0.
#140000
b1 +
b1 <
b1 ^
b0 !
b0 2
b0 Y
b0 c
b0 *
b0 ;
b0 \
b0 e
b1 )
b1 :
b1 [
b1 d
1]
b11 q
b1000 r
b111 s
1.
#145000
0.
#150000
1"
b0 +
b0 <
b0 ^
13
b0 )
b0 :
b0 [
b0 d
0]
b1000000000 q
b0 r
b1000 s
1.
#155000
0.
#160000
1$
0"
16
03
1'
b10 !
b10 2
b10 Y
b10 c
b1 *
b1 ;
b1 \
b1 e
b10 )
b10 :
b10 [
b10 d
b1000101001100 q
b1 r
b0 s
1.
#165000
0.
#170000
0$
06
0'
b1001100 q
b110 r
b1 s
1.
b11000 U
b11000 a
b100 X
b11100001100001110100 -
b11100001100001110100 1
#175000
0.
#180000
b11 +
b11 <
b11 ^
b0 !
b0 2
b0 Y
b0 c
b0 *
b0 ;
b0 \
b0 e
b0 )
b0 :
b0 [
b0 d
1]
b1 q
b1000 r
b110 s
1.
#185000
0.
#190000
1"
b0 +
b0 <
b0 ^
13
0]
b1000000000 q
b0 r
b1000 s
1.
#195000
0.
#200000
1$
0"
16
03
1'
b10 !
b10 2
b10 Y
b10 c
b1 *
b1 ;
b1 \
b1 e
b10 )
b10 :
b10 [
b10 d
b1000101001100 q
b1 r
b0 s
1.
#205000
0.
#210000
0$
06
0'
b1001100 q
b110 r
b1 s
1.
b0 U
b0 a
b101 X
b11100000000000110101 -
b11100000000000110101 1
#215000
0.
#220000
b10 +
b10 <
b10 ^
b0 !
b0 2
b0 Y
b0 c
b0 *
b0 ;
b0 \
b0 e
b0 )
b0 :
b0 [
b0 d
1]
b1 q
b1000 r
b110 s
1.
#225000
0.
#230000
1"
b0 +
b0 <
b0 ^
13
0]
b1000000000 q
b0 r
b1000 s
1.
#235000
0.
#240000
1$
0"
16
03
1'
b10 !
b10 2
b10 Y
b10 c
b1 *
b1 ;
b1 \
b1 e
b10 )
b10 :
b10 [
b10 d
b1000101001100 q
b1 r
b0 s
1.
#245000
0.
#250000
0$
06
0'
b1001100 q
b110 r
b1 s
1.
b1000 U
b1000 a
b11100000100001010101 -
b11100000100001010101 1
#255000
0.
#260000
b0 !
b0 2
b0 Y
b0 c
b0 *
b0 ;
b0 \
b0 e
b0 )
b0 :
b0 [
b0 d
1]
b1 q
b1000 r
b110 s
1.
#265000
0.
#270000
1"
13
0]
b1000000000 q
b0 r
b1000 s
1.
#275000
0.
#280000
1$
0"
16
03
1'
b10 !
b10 2
b10 Y
b10 c
b1 *
b1 ;
b1 \
b1 e
b10 )
b10 :
b10 [
b10 d
b1000101001100 q
b1 r
b0 s
1.
#285000
0.
#290000
0$
06
0'
b1001100 q
b110 r
b1 s
1.
b10 J
b101 U
b101 a
b1000 X
b10 ,
b10 0
b10 =
b11100000010101011000 -
b11100000010101011000 1
#295000
0.
#300000
xO
xK
bx ?
b11 R
b11 9
b11 A
b11 _
b1 +
b1 <
b1 ^
b0 !
b0 2
b0 Y
b0 c
b0 *
b0 ;
b0 \
b0 e
b0 )
b0 :
b0 [
b0 d
1]
b1 q
b1000 r
b110 s
1.
#305000
0.
#310000
b0 R
1"
b0 9
b0 A
b0 _
b0 +
b0 <
b0 ^
13
0]
xO
xK
b1000000000 q
b0 r
bx ?
b11 T
b1000 s
1.
#315000
0.
#320000
1$
0"
16
03
1'
b10 !
b10 2
b10 Y
b10 c
b1 *
b1 ;
b1 \
b1 e
b10 )
b10 :
b10 [
b10 d
b1000101001100 q
b1 r
0O
0K
b0 s
b0 ?
b0 T
1.
#325000
0.
#330000
0$
06
0'
b1001100 q
b1001 r
b1 s
1.
b1 #
b1 4
b1 `
0B
b0 J
b10 &
b10 8
b10 V
b10 W
b10 b
b100000 U
b100000 a
b0 X
b0 >
b0 C
b0 ,
b0 0
b0 =
b1010000000000000 -
b1010000000000000 1
#335000
0.
#340000
15
1Z
b10 *
b10 ;
b10 \
b10 e
b1 )
b1 :
b1 [
b1 d
b100001010010 q
b0 r
b1001 s
1.
#345000
0.
#350000
1$
05
16
0Z
1'
b1 *
b1 ;
b1 \
b1 e
b10 )
b10 :
b10 [
b10 d
b1000101001100 q
b1 r
b0 s
1.
#355000
0.
#360000
0$
06
0'
b1001100 q
b110 r
b1 s
1.
b0 #
b0 4
b0 `
1B
b0 &
b0 8
b0 V
b0 W
b0 b
b101 U
b101 a
b1000 X
b1110 >
b1110 C
b11100000010100111000 -
b11100000010100111000 1
#365000
0.
#370000
xO
xK
bx ?
b11 R
b11 9
b11 A
b11 _
b1 +
b1 <
b1 ^
b0 !
b0 2
b0 Y
b0 c
b0 *
b0 ;
b0 \
b0 e
b0 )
b0 :
b0 [
b0 d
1]
b1 q
b1000 r
b110 s
1.
#375000
0.
#380000
b0 R
1"
b0 9
b0 A
b0 _
b0 +
b0 <
b0 ^
13
0]
b1000000000 q
b0 r
xO
xK
b1000 s
bx ?
b11 T
1.
#385000
0.
#390000
1$
0"
16
03
1'
b10 !
b10 2
b10 Y
b10 c
b1 *
b1 ;
b1 \
b1 e
b10 )
b10 :
b10 [
b10 d
0O
0K
b1000101001100 q
b1 r
b0 ?
b0 T
b0 s
1.
#395000
0.
#400000
0$
06
0'
b1001100 q
b1001 r
b1 s
1.
b1 #
b1 4
b1 `
b10 &
b10 8
b10 V
b10 W
b10 b
b100000 U
b100000 a
b0 X
b1010 >
b1010 C
b10101010000000000000 -
b10101010000000000000 1
#405000
0.
#410000
1$
15
1Z
b10 *
b10 ;
b10 \
b10 e
b1 )
b1 :
b1 [
b1 d
b100001010010 q
b0 r
b1001 s
1.
#415000
0.
#420000
05
16
0Z
1'
b1 *
b1 ;
b1 \
b1 e
b10 )
b10 :
b10 [
b10 d
b1000101001100 q
b1 r
b0 s
1.
#425000
0.
#430000
0$
06
0'
b1001100 q
b111 r
b1 s
1.
b0 #
b0 4
b0 `
b0 &
b0 8
b0 V
b0 W
b0 b
b101000 U
b101000 a
b101 X
b1110 >
b1110 C
b11100010100000000101 -
b11100010100000000101 1
#435000
0.
#440000
b0 !
b0 2
b0 Y
b0 c
b0 *
b0 ;
b0 \
b0 e
b1 )
b1 :
b1 [
b1 d
1]
b11 q
b1000 r
b111 s
1.
#445000
0.
#450000
1"
13
b0 )
b0 :
b0 [
b0 d
0]
b1000000000 q
b0 r
b1000 s
1.
#455000
0.
#460000
1$
0"
16
03
1'
b10 !
b10 2
b10 Y
b10 c
b1 *
b1 ;
b1 \
b1 e
b10 )
b10 :
b10 [
b10 d
b1000101001100 q
b1 r
b0 s
1.
#465000
0.
#470000
0$
06
0'
b1001100 q
b110 r
b1 s
1.
b10 N
b101 U
b101 a
b1000 X
b1000 ,
b1000 0
b1000 =
b11100000010101111000 -
b11100000010101111000 1
#475000
0.
#480000
xO
xK
bx ?
b11 R
b11 9
b11 A
b11 _
b1 +
b1 <
b1 ^
b0 !
b0 2
b0 Y
b0 c
b0 *
b0 ;
b0 \
b0 e
b0 )
b0 :
b0 [
b0 d
1]
b1 q
b1000 r
b110 s
1.
#485000
0.
#490000
b0 R
1"
b0 9
b0 A
b0 _
b0 +
b0 <
b0 ^
13
0]
xO
xK
b1000000000 q
b0 r
bx ?
b11 T
b1000 s
1.
#495000
0.
#500000
1$
0"
16
03
1'
b10 !
b10 2
b10 Y
b10 c
b1 *
b1 ;
b1 \
b1 e
b10 )
b10 :
b10 [
b10 d
b1000101001100 q
b1 r
0O
0K
b0 s
b0 ?
b0 T
1.
#505000
0.
#510000
0$
06
0'
b1001100 q
b111 r
b1 s
1.
0B
b0 N
b101000 U
b101000 a
b111 X
b1011 >
b1011 C
b0 ,
b0 0
b0 =
b10110010100001010111 -
b10110010100001010111 1
#515000
0.
#520000
b0 !
b0 2
b0 Y
b0 c
b0 *
b0 ;
b0 \
b0 e
b1 )
b1 :
b1 [
b1 d
1]
b11 q
b1000 r
b111 s
1.
#525000
0.
#530000
13
b0 )
b0 :
b0 [
b0 d
0]
b1000000000 q
b0 r
b1000 s
1.
#535000
0.
